numpyXtns/__init__.py
numpyXtns/numpyXtns.py
numpyXtns/spaef.py
numpyXtns-20.4.1.dist-info/LICENSE.txt
numpyXtns-20.4.1.dist-info/METADATA
numpyXtns-20.4.1.dist-info/WHEEL
numpyXtns-20.4.1.dist-info/top_level.txt
numpyXtns-20.4.1.dist-info/RECORD
